GPminer/__init__.py
GPminer/eval.py
GPminer/gen.py
GPminer/ind.py
GPminer/ino.py
GPminer/popu.py
GPstrat-1.0.0.dist-info/LICENSE
GPstrat-1.0.0.dist-info/METADATA
GPstrat-1.0.0.dist-info/WHEEL
GPstrat-1.0.0.dist-info/top_level.txt
GPstrat-1.0.0.dist-info/RECORD
