Metadata-Version: 2.1
Name: GPstrat
Version: 1.0.0
Summary: Package for backtest
Home-page: https://github.com/LHanLi/GPstrat
Author: LH.Li
Author-email: lh98lee@zju.edu.cn
Classifier: Programming Language :: Python :: 3
Classifier: License :: OSI Approved :: GNU General Public License v3 or later (GPLv3+)
Classifier: Operating System :: OS Independent
License-File: LICENSE
